_scs_indirect.cpython-311-darwin.so
_scs_direct.cpython-311-darwin.so
scs/__init__.py
scs-3.2.5.dist-info/RECORD
scs-3.2.5.dist-info/LICENSE
scs-3.2.5.dist-info/WHEEL
scs-3.2.5.dist-info/METADATA
