Metadata-Version: 2.1
Name: scs
Version: 3.2.5
Summary: Splitting conic solver
Author-Email: Brendan O'Donoghue <bodonoghue85@gmail.com>
License: MIT License
Requires-Python: >=3.7
Requires-Dist: numpy
Requires-Dist: scipy
